{
  "_fv": 47,
  "_type": "rangeditem",
  "definition": {
    "renderType": 0,
    "texture": "sarbakan",
    "customModelName": "Normal",
    "name": "Sarbakan",
    "specialInfo": [],
    "creativeTab": {
      "value": "CUSTOM:ToolsAndArmor"
    },
    "stackSize": 1,
    "ammoItem": {
      "value": "CUSTOM:Dart"
    },
    "shootConstantly": false,
    "usageCount": 76,
    "actionSound": {
      "value": "entity.arrow.shoot"
    },
    "hasGlow": false,
    "animation": "spear",
    "enableMeleeDamage": false,
    "damageVsEntity": 0.0,
    "bulletPower": 0.7,
    "bulletDamage": 1.0,
    "bulletKnockback": 1,
    "bulletParticles": false,
    "bulletIgnitesFire": false,
    "bulletItemTexture": {
      "value": "CUSTOM:Dart"
    },
    "bulletModel": "Modeldart",
    "customBulletModelTexture": "dart.png",
    "onBulletHitsEntity": {
      "name": "SarbakanKoghdaSnariadPopadaietVSushchnost"
    }
  }
}